<?xml version="1.0"?>
<qmcsystem>
  <wavefunction name="psi0" target="e">
    <determinantset type="MolecularOrbital" name="LCAOBSet" source="ion0" transform="yes" href="Zn.log.h5">
      <slaterdeterminant>
        <determinant id="updet" size="10">
          <occupation mode="ground"/>
          <coefficient size="144" spindataset="0"/>
        </determinant>
        <determinant id="downdet" size="10">
          <occupation mode="ground"/>
          <coefficient size="144" spindataset="0"/>
        </determinant>
      </slaterdeterminant>
    </determinantset>
    <jastrow name="J2" type="Two-Body" function="Bspline" print="yes">
      <correlation rcut="12.1" size="10" speciesA="u" speciesB="u">
        <coefficients id="uu" type="Array"> 0.09907309715 -0.04218220149 -0.05510768673 -0.04114369192 -0.04325518066 -0.05253797583 -0.04728577091 0.003283267913 0.07221971716 0.09536428172</coefficients>
      </correlation>
      <correlation rcut="12.1" size="10" speciesA="u" speciesB="d">
        <coefficients id="ud" type="Array"> 0.5012950392 0.2059821708 0.04984762157 0.002148794917 -0.03382116497 -0.0782372823 -0.08867868593 -0.1211007319 -0.1046791218 -0.09236001104</coefficients>
      </correlation>
    </jastrow>
    <jastrow name="J1" type="One-Body" function="Bspline" source="ion0" print="yes">
      <correlation rcut="12.1" size="10" cusp="0" elementType="Zn">
        <coefficients id="eZn" type="Array"> -3.312797303 -1.523522204 0.3985871116 0.9884290759 0.8033670456 0.7960610925 1.005430649 0.707236421 0.1549072275 -0.0009523123515</coefficients>
      </correlation>
    </jastrow>
    <jastrow name="J3" type="eeI" function="polynomial" source="ion0" print="yes">
      <correlation ispecies="Zn" especies="u" isize="3" esize="3" rcut="12.1">
        <coefficients id="uuZn" type="Array" optimize="yes"> 2.911853994e-06 -9.660308291e-07 -1.748222207e-06 -3.725866893e-06 -5.865532945e-07 -1.912597182e-06 -7.432977205e-07 1.788692625e-07 1.943186205e-06 -2.94961604e-06 -2.624831979e-06 -2.661704647e-07 -5.092981234e-07 3.557910537e-06 6.379371412e-07 -1.909416257e-08 2.762959885e-06 3.883503145e-06 -9.524556071e-07 1.153007439e-07 -1.512696375e-06 7.015945998e-08 4.233667223e-09 5.121638323e-07 -5.222843666e-08 2.470424817e-09</coefficients>
      </correlation>
      <correlation ispecies="Zn" especies1="u" especies2="d" isize="3" esize="3" rcut="12.1">
        <coefficients id="udZn" type="Array" optimize="yes"> 6.759545034e-06 4.179273545e-06 -5.624686985e-06 -6.468327312e-06 -8.554595794e-07 1.159942464e-06 3.669146685e-06 -9.923221684e-06 -2.41773163e-06 -5.526959476e-06 -6.208946129e-06 8.687908429e-06 -4.103262691e-07 7.393345784e-06 -1.137811221e-07 4.505407147e-08 1.085908444e-05 7.904427391e-06 -7.609934726e-06 8.458908555e-07 -4.865838039e-06 1.120153104e-06 -1.578073589e-07 1.841728169e-06 -2.877003771e-07 3.898996593e-08</coefficients>
      </correlation>
    </jastrow>
  </wavefunction>
</qmcsystem>
