<?xml version="1.0"?>
<qmcsystem>
  <wavefunction name="psi0" target="e">
    <determinantset type="MolecularOrbital" name="LCAOBSet" source="ion0" transform="yes" href="Be.log.orbs.h5">
      <slaterdeterminant>
        <determinant id="updet" size="1">
          <occupation mode="ground"/>
          <coefficient size="54" spindataset="0"/>
        </determinant>
        <determinant id="downdet" size="1">
          <occupation mode="ground"/>
          <coefficient size="54" spindataset="0"/>
        </determinant>
      </slaterdeterminant>
    </determinantset>
    <jastrow name="J2" type="Two-Body" function="Bspline" print="yes">
      <correlation rcut="10.0" size="10" speciesA="u" speciesB="d">
        <coefficients id="ud" type="Array"> 1.421883492 1.031993152 0.6516121151 0.3689276185 0.1462645089 -0.04053019503 -0.1934634907 -0.318972314 -0.3797364732 -0.4193440363</coefficients>
      </correlation>
    </jastrow>
    <jastrow name="J1" type="One-Body" function="Bspline" source="ion0" print="yes">
      <correlation rcut="10.0" size="10" cusp="0" elementType="Be">
        <coefficients id="eBe" type="Array"> -1.226562499 -0.4364791625 -0.3610103251 -0.1497203552 0.01206243256 0.1973000894 0.3409414044 0.4626516735 0.4929832578 0.3922042066</coefficients>
      </correlation>
    </jastrow>
    <jastrow name="J3" type="eeI" function="polynomial" source="ion0" print="yes">
      <correlation ispecies="Be" especies="u" isize="3" esize="3" rcut="10.0">
        <coefficients id="uuBe" type="Array" optimize="yes">
        </coefficients>
      </correlation>
      <correlation ispecies="Be" especies1="u" especies2="d" isize="3" esize="3" rcut="10.0">
        <coefficients id="udBe" type="Array" optimize="yes">
        </coefficients>
      </correlation>
    </jastrow>
  </wavefunction>
</qmcsystem>
