<?xml version="1.0"?>
<qmcsystem>
  <wavefunction name="psi0" target="e">
    <determinantset type="MolecularOrbital" name="LCAOBSet" source="ion0" transform="yes" href="Cu.log.h5">
      <slaterdeterminant>
        <determinant id="updet" size="10">
          <occupation mode="ground"/>
          <coefficient size="144" spindataset="0"/>
        </determinant>
        <determinant id="downdet" size="9">
          <occupation mode="ground"/>
          <coefficient size="144" spindataset="0"/>
        </determinant>
      </slaterdeterminant>
    </determinantset>
    <jastrow name="J2" type="Two-Body" function="Bspline" print="yes">
      <correlation rcut="12.1" size="10" speciesA="u" speciesB="u">
        <coefficients id="uu" type="Array"> 0.2003474935 0.04264163622 -0.003211208993 -0.02779681845 -0.05942040142 -0.07828787342 -0.06771133625 -0.02734804978 -0.006292271218 0.01018062941</coefficients>
      </correlation>
      <correlation rcut="12.1" size="10" speciesA="u" speciesB="d">
        <coefficients id="ud" type="Array"> 0.2964206728 0.0450644639 -0.04023663615 -0.03485279516 -0.04034483654 -0.0759279404 -0.0637132697 -0.04164276707 -0.009546171393 -0.004730480535</coefficients>
      </correlation>
    </jastrow>
    <jastrow name="J1" type="One-Body" function="Bspline" source="ion0" print="yes">
      <correlation rcut="12.1" size="10" cusp="0" elementType="Cu">
        <coefficients id="eCu" type="Array"> -2.553916253 -1.120631156 0.3211564744 0.7448815843 0.7154408411 0.7746158612 0.7468793234 0.3378328906 0.04664489874 -0.01005193028</coefficients>
      </correlation>
    </jastrow>
    <jastrow name="J3" type="eeI" function="polynomial" source="ion0" print="yes">
      <correlation ispecies="Cu" especies="u" isize="3" esize="3" rcut="12.1">
        <coefficients id="uuCu" type="Array" optimize="yes"> 2.613477774e-06 -3.046056066e-07 -1.575883772e-06 -3.320608344e-06 -4.464920225e-07 -8.533046211e-07 -1.880869684e-06 7.255287949e-07 1.997564168e-06 -1.100903232e-06 -2.175190474e-06 -3.331458545e-07 -5.827012902e-07 3.11792964e-06 7.621483188e-07 -2.195995819e-08 4.996775347e-07 4.234177285e-06 -1.065283271e-06 1.85257454e-07 -1.055480595e-06 2.191437482e-08 4.808495092e-09 6.253054587e-07 -3.436101857e-08 -2.441216051e-10</coefficients>
      </correlation>
      <correlation ispecies="Cu" especies1="u" especies2="d" isize="3" esize="3" rcut="12.1">
        <coefficients id="udCu" type="Array" optimize="yes"> 5.641245863e-06 3.919655516e-06 -3.845859447e-06 -5.908045589e-06 -9.040338392e-07 3.833884496e-07 4.341027728e-06 -8.27115167e-06 -9.118721555e-07 -6.010415994e-06 -5.276400241e-06 5.985619575e-06 -4.306234057e-07 6.643717576e-06 -2.526360207e-08 3.627121369e-08 1.058349035e-05 6.085536976e-06 -5.484222008e-06 6.047109958e-07 -4.351775246e-06 8.430965971e-07 -1.12236022e-07 1.759802657e-06 -2.304346556e-07 3.002814476e-08</coefficients>
      </correlation>
    </jastrow>
  </wavefunction>
</qmcsystem>
