<?xml version="1.0"?>
<qmcsystem>
  <wavefunction name="psi0" target="e">
    <determinantset type="MolecularOrbital" name="LCAOBSet" source="ion0" transform="yes" href="V.log.h5">
      <slaterdeterminant>
        <determinant id="updet" size="8">
          <occupation mode="ground"/>
          <coefficient size="10" spindataset="0"/>
        </determinant>
        <determinant id="downdet" size="5">
          <occupation mode="ground"/>
          <coefficient size="10" spindataset="0"/>
        </determinant>
      </slaterdeterminant>
    </determinantset>
    <jastrow name="J2" type="Two-Body" function="Bspline" print="yes">
      <correlation rcut="12.0" size="10" speciesA="u" speciesB="u">
        <coefficients id="uu" type="Array"> 0.2260031832 0.03972315689 -0.03213301751 -0.06463852396 -0.06595005602 -0.05980593806 -0.03548229949 -0.007365478525 0.01387871266 0.01363266195</coefficients>
      </correlation>
      <correlation rcut="12.0" size="10" speciesA="u" speciesB="d">
        <coefficients id="ud" type="Array"> 0.3232990909 0.0831288158 0.009398512134 -0.03363670509 -0.04794522703 -0.05898639848 -0.05256604126 -0.04552636371 -0.04082633792 -0.02786710246</coefficients>
      </correlation>
    </jastrow>
    <jastrow name="J1" type="One-Body" function="Bspline" source="ion0" print="yes">
      <correlation rcut="12.0" size="10" cusp="0" elementType="V">
        <coefficients id="eV" type="Array"> -1.376034958 -0.6200444802 0.05148408531 0.3675733662 0.5193351421 0.5004134335 0.3557865601 0.1632212414 0.04586185981 0.004673355903</coefficients>
      </correlation>
    </jastrow>
    <jastrow name="J3" type="eeI" function="polynomial" source="ion0" print="yes">
      <correlation ispecies="V" especies="u" isize="3" esize="3" rcut="12.0">
        <coefficients id="uuV" type="Array" optimize="no">
        </coefficients>
      </correlation>
      <correlation ispecies="V" especies1="u" especies2="d" isize="3" esize="3" rcut="12.0">
        <coefficients id="udV" type="Array" optimize="no">
        </coefficients>
      </correlation>
    </jastrow>
  </wavefunction>
</qmcsystem>
